maplargerest/__init__.py
maplargerest/endpoints.py
maplargerest/models.py
maplargerest-4.110.dev20250730195004.dist-info/licenses/LICENSE.txt
maplargerest-4.110.dev20250730195004.dist-info/METADATA
maplargerest-4.110.dev20250730195004.dist-info/WHEEL
maplargerest-4.110.dev20250730195004.dist-info/top_level.txt
maplargerest-4.110.dev20250730195004.dist-info/RECORD
