Metadata-Version: 2.4
Name: maplargerest
Version: 4.110.dev20250730195004
Summary: MapLarge REST API Python Client
Author-email: MapLarge DevOps <maplarge.devops@maplarge.com>
License: MIT
Project-URL: Homepage, https://maplarge.com
Project-URL: Issues, https://maplarge.com
Classifier: Development Status :: 5 - Production/Stable
Classifier: Intended Audience :: Developers
Classifier: Operating System :: OS Independent
Classifier: Programming Language :: Python
Classifier: Programming Language :: Python :: 3
Classifier: Programming Language :: Python :: 3.8
Classifier: Programming Language :: Python :: 3.9
Classifier: Programming Language :: Python :: 3.10
Classifier: Programming Language :: Python :: 3.11
Classifier: Programming Language :: Python :: 3.12
Classifier: Programming Language :: Python :: 3 :: Only
Classifier: Topic :: Scientific/Engineering :: GIS
Classifier: Typing :: Typed
Requires-Python: >=3.8
License-File: LICENSE.txt
Requires-Dist: python-dateutil
Dynamic: license-file
Dynamic: requires-dist
